{"edges":[{"confidence":"EXTRACTED","confidence_score":1.0,"relation":"imports","source":"lib","source_file":"./crates/cirrus-callbacks/src/lib.rs","source_location":"L26","target":"document_name","weight":1.0},{"confidence":"EXTRACTED","confidence_score":1.0,"relation":"imports","source":"lib","source_file":"./crates/cirrus-callbacks/src/lib.rs","source_location":"L19","target":"serializer_zmqdocumentsink","weight":1.0},{"confidence":"EXTRACTED","confidence_score":1.0,"relation":"imports","source":"lib","source_file":"./crates/cirrus-callbacks/src/lib.rs","source_location":"L14","target":"capturingsink_jsonlsink_stderrtracesink","weight":1.0},{"confidence":"EXTRACTED","confidence_score":1.0,"relation":"imports","source":"lib","source_file":"./crates/cirrus-callbacks/src/lib.rs","source_location":"L24","target":"tiledsink","weight":1.0}],"hyperedges":[],"input_tokens":0,"nodes":[{"confidence":"EXTRACTED","confidence_score":1.0,"file_type":"code","id":"lib","label":"lib","source_file":"./crates/cirrus-callbacks/src/lib.rs","source_location":"L1"}],"output_tokens":0}